fierpy/__init__.py
fierpy/fier.py
fierpy-0.0.4.dist-info/LICENSE
fierpy-0.0.4.dist-info/METADATA
fierpy-0.0.4.dist-info/WHEEL
fierpy-0.0.4.dist-info/top_level.txt
fierpy-0.0.4.dist-info/RECORD
