Metadata-Version: 2.1
Name: fierpy
Version: 0.0.4
Summary: Python implementation of the Forecasting Inundation Extents using REOF method
Home-page: http://github.com/servir/fierpy
Author: Kel Markert
Author-email: kel.markert@gmail.com
License: MIT
Platform: UNKNOWN
Requires-Dist: numpy
Requires-Dist: pandas
Requires-Dist: xarray
Requires-Dist: scikit-learn (>=0.24)
Requires-Dist: geoglows
Requires-Dist: eofs
Requires-Dist: netcdf4
Provides-Extra: opensarlab
Requires-Dist: kernda ; extra == 'opensarlab'
Requires-Dist: jupyter ; extra == 'opensarlab'
